MANIFEST.in
README.txt
setup.cfg
setup.py
csci/__init__.py
csci.postfeeds.egg-info/PKG-INFO
csci.postfeeds.egg-info/SOURCES.txt
csci.postfeeds.egg-info/dependency_links.txt
csci.postfeeds.egg-info/entry_points.txt
csci.postfeeds.egg-info/namespace_packages.txt
csci.postfeeds.egg-info/not-zip-safe
csci.postfeeds.egg-info/paster_plugins.txt
csci.postfeeds.egg-info/pkg-info
csci.postfeeds.egg-info/requires.txt
csci.postfeeds.egg-info/sources.txt
csci.postfeeds.egg-info/top_level.txt
csci/postfeeds/README.txt
csci/postfeeds/__init__.py
csci/postfeeds/config.py
csci/postfeeds/configure.zcml
csci/postfeeds/browser/__init__.py
csci/postfeeds/browser/configure.zcml
csci/postfeeds/browser/postfeedsview.pt
csci/postfeeds/browser/postfeedsview.py
csci/postfeeds/browser/lib/__init__.py
csci/postfeeds/browser/lib/feedparser.py
csci/postfeeds/browser/lib/google_short.py
csci/postfeeds/browser/lib/twitter.py
csci/postfeeds/content/__init__.py
csci/postfeeds/content/configure.zcml
csci/postfeeds/content/postfeed.py
csci/postfeeds/interfaces/__init__.py
csci/postfeeds/interfaces/postfeed.py
csci/postfeeds/portlets/__init__.py
csci/postfeeds/portlets/configure.zcml
csci/postfeeds/profiles/default/factorytool.xml
csci/postfeeds/profiles/default/metadata.xml
csci/postfeeds/profiles/default/portlets.xml
csci/postfeeds/profiles/default/rolemap.xml
csci/postfeeds/profiles/default/types.xml
csci/postfeeds/profiles/default/types/postfeed.xml
csci/postfeeds/tests/__init__.py
csci/postfeeds/tests/base.py
csci/postfeeds/tests/test_doctest.py