Metadata-Version: 1.0
Name: csci.postfeeds
Version: 1.1dev
Summary: plone rss news feeds twitter posting
Home-page: http://www.cannonscientific.com
Author: Peter Dyson
Author-email: pdyson@cannonscientific.com
License: GPL
Keywords: plone rss news feeds atom twitter posting
Platform: UNKNOWN
Classifier: Framework :: Plone
Classifier: Intended Audience :: Developers
Classifier: Topic :: Software Development :: Libraries :: Python Modules
Classifier: License :: OSI Approved :: GNU General Public License (GPL)
